LICENSE
README.md
liteyuki/EN.LICENSE
liteyuki/LICENSE
liteyuki/__init__.py
liteyuki/bot/__init__.py
liteyuki/bot/lifespan.py
liteyuki/comm/__init__.py
liteyuki/comm/channel.py
liteyuki/comm/event.py
liteyuki/comm/storage.py
liteyuki/config.py
liteyuki/core/__init__.py
liteyuki/core/manager.py
liteyuki/dev/__init__.py
liteyuki/dev/observer.py
liteyuki/dev/plugin.py
liteyuki/exception.py
liteyuki/log.py
liteyuki/mkdoc.py
liteyuki/plugin/__init__.py
liteyuki/plugin/load.py
liteyuki/plugin/manager.py
liteyuki/plugin/model.py
liteyuki/plugins/__init__.py
liteyuki/plugins/liteecho.py
liteyuki/plugins/plugin_loader/__init__.py
liteyuki/py.typed
liteyuki/session/__init__.py
liteyuki/session/event.py
liteyuki/session/matcher.py
liteyuki/session/message/segments.py
liteyuki/session/models.py
liteyuki/session/on.py
liteyuki/session/rule.py
liteyuki/utils.py
liteyukibot-6.3.16.dist-info/METADATA
liteyukibot-6.3.16.dist-info/WHEEL
liteyukibot-6.3.16.dist-info/entry_points.txt
liteyukibot-6.3.16.dist-info/licenses/LICENSE
liteyukibot-6.3.16.dist-info/RECORD
