Metadata-Version: 2.1
Name: liteyukibot
Version: 6.3.16
Summary: A lightweight bot process management framework and application.
Author-Email: snowykami <snowykami@outlook.com>
License: MIT&LSO
Project-URL: Homepage, https://bot.liteyuki.icu
Project-URL: Repository, https://github.com/LiteyukiStudio/LiteyukiBot
Project-URL: Issue tracker, https://github.com/LiteyukiStudio/LiteyukiBot/issues/new?assignees=&labels=&projects=&template=%E9%97%AE%E9%A2%98%E5%8F%8D%E9%A6%88.md&title=
Requires-Python: >=3.10
Requires-Dist: loguru~=0.7.2
Requires-Dist: pydantic>=2.9.2
Requires-Dist: PyYAML>=6.0.2
Requires-Dist: toml>=0.10.2
Requires-Dist: watchdog>=4.0.1
Requires-Dist: pdm-backend>=2.3.3
Requires-Dist: magicoca>=1.0.6
Requires-Dist: croterline>=1.0.9
